<?xml version="1.0" encoding="UTF-8"?>
<root>
    <row>
        <key>1</key>
        <code>401013</code>
        <fullname>ABDOMEN SIMPLE                                                        </fullname>
        <shortname>ABDS</shortname>
        <modalidad>Rayos</modalidad>
    </row>
    <row>
        <key>2</key>
        <code>401031</code>
        <fullname>ATM                                                                   </fullname>
        <shortname>ATM</shortname>
        <modalidad>Rayos</modalidad>
    </row>
    <row>
        <key>3</key>
        <code>401054</code>
        <fullname>BRAZO                                                                 </fullname>
        <shortname>BRA</shortname>
        <modalidad>Rayos</modalidad>
    </row>
    <row>
        <key>4</key>
        <code>401051</code>
        <fullname>CADERA                                                                </fullname>
        <shortname>CAD</shortname>
        <modalidad>Rayos</modalidad>
    </row>
    <row>
        <key>5</key>
        <code>401052</code>
        <fullname>CADERA EXTRA                                                          </fullname>
        <shortname>CADE</shortname>
        <modalidad>Rayos</modalidad>
    </row>
    <row>
        <key>8</key>
        <code>401054</code>
        <fullname>CODO                                                                  </fullname>
        <shortname>COD</shortname>
        <modalidad>Rayos</modalidad>
    </row>
    <row>
        <key>11</key>
        <code>401042</code>
        <fullname>COLUMNA CERVICAL                                                      </fullname>
        <shortname>CC</shortname>
        <modalidad>Rayos</modalidad>
    </row>
    <row>
        <key>12</key>
        <code>401044</code>
        <fullname>COLUMNA CERVICAL FUNCIONALES                                          </fullname>
        <shortname>CCF</shortname>
        <modalidad>Rayos</modalidad>
    </row>
    <row>
        <key>13</key>
        <code>401043</code>
        <fullname>COLUMNA CERVICAL OBLICUAS                                             </fullname>
        <shortname>CCO</shortname>
        <modalidad>Rayos</modalidad>
    </row>
    <row>
        <key>14</key>
        <code>401045</code>
        <fullname>COLUMNA DORSAL                                                        </fullname>
        <shortname>CD</shortname>
        <modalidad>Rayos</modalidad>
    </row>
    <row>
        <key>15</key>
        <code>401045</code>
        <fullname>COLUMNA DORSAL OBLICUAS                                               </fullname>
        <shortname>CDO</shortname>
        <modalidad>Rayos</modalidad>
    </row>
    <row>
        <key>16</key>
        <code>401045</code>
        <fullname>COLUMNA DORSOLUMBAR                                                   </fullname>
        <shortname>CDL</shortname>
        <modalidad>Rayos</modalidad>
    </row>
    <row>
        <key>18</key>
        <code>401046</code>
        <fullname>COLUMNA LUMBOSACRA                                                    </fullname>
        <shortname>CLS</shortname>
        <modalidad>Rayos</modalidad>
    </row>
    <row>
        <key>19</key>
        <code>401048</code>
        <fullname>COLUMNA LUMBOSACRA OBLICUAS                                           </fullname>
        <shortname>CLSO</shortname>
        <modalidad>Rayos</modalidad>
    </row>
    <row>
        <key>20</key>
        <code>401049</code>
        <fullname>COLUMNA TOTAL O DORSOLUMBAR PANORAMICA                                </fullname>
        <shortname>CT</shortname>
        <modalidad>Rayos</modalidad>
    </row>
    <row>
        <key>22</key>
        <code>401060</code>
        <fullname>COSTILLAS                                                             </fullname>
        <shortname>COS</shortname>
        <modalidad>Rayos</modalidad>
    </row>
    <row>
        <key>23</key>
        <code>401031</code>
        <fullname>CP                                                                    </fullname>
        <shortname>CP</shortname>
        <modalidad>Rayos</modalidad>
    </row>
    <row>
        <key>24</key>
        <code>401032</code>
        <fullname>CRANEO                                                                </fullname>
        <shortname>CRA</shortname>
        <modalidad>Rayos</modalidad>
    </row>
    <row>
        <key>25</key>
        <code>401033</code>
        <fullname>CRANEO EXTRA                                                          </fullname>
        <shortname>CRAE</shortname>
        <modalidad>Rayos</modalidad>
    </row>
    <row>
        <key>29</key>
        <code>401060</code>
        <fullname>ESTERNON                                                              </fullname>
        <shortname>EST</shortname>
        <modalidad>Rayos</modalidad>
    </row>
    <row>
        <key>31</key>
        <code>401060</code>
        <fullname>FEMUR                                                                 </fullname>
        <shortname>FEM</shortname>
        <modalidad>Rayos</modalidad>
    </row>
    <row>
        <key>32</key>
        <code>401060</code>
        <fullname>HOMBRO                                                                </fullname>
        <shortname>HOM</shortname>
        <modalidad>Rayos</modalidad>
    </row>
    <row>
        <key>33</key>
        <code>401002</code>
        <fullname>CAVUM, LARINGE                                                        </fullname>
        <shortname>CVM</shortname>
        <modalidad>Rayos</modalidad>
    </row>
    <row>
        <key>36</key>
        <code>401054</code>
        <fullname>MANO                                                                  </fullname>
        <shortname>MAN</shortname>
        <modalidad>Rayos</modalidad>
    </row>
    <row>
        <key>37</key>
        <code>401056</code>
        <fullname>MANO EDAD OSEA                                                        </fullname>
        <shortname>MEO</shortname>
        <modalidad>Rayos</modalidad>
    </row>
    <row>
        <key>38</key>
        <code>401031</code>
        <fullname>MAXILAR INFERIOR                                                      </fullname>
        <shortname>MXI</shortname>
        <modalidad>Rayos</modalidad>
    </row>
    <row>
        <key>39</key>
        <code>401031</code>
        <fullname>MAXILAR SUPERIOR                                                      </fullname>
        <shortname>MXS</shortname>
        <modalidad>Rayos</modalidad>
    </row>
    <row>
        <key>40</key>
        <code>401054</code>
        <fullname>MUÑECA                                                                </fullname>
        <shortname>MUÑ</shortname>
        <modalidad>Rayos</modalidad>
    </row>
    <row>
        <key>41</key>
        <code>401031</code>
        <fullname>NARIZ                                                                 </fullname>
        <shortname>NAR</shortname>
        <modalidad>Rayos</modalidad>
    </row>
    <row>
        <key>42</key>
        <code>401035</code>
        <fullname>OIDO                                                                  </fullname>
        <shortname>OID</shortname>
        <modalidad>Rayos</modalidad>
    </row>
    <row>
        <key>43</key>
        <code>401031</code>
        <fullname>ORBITA                                                                </fullname>
        <shortname>ORB</shortname>
        <modalidad>Rayos</modalidad>
    </row>
    <row>
        <key>44</key>
        <code>401051</code>
        <fullname>PELVIS                                                                </fullname>
        <shortname>PEL</shortname>
        <modalidad>Rayos</modalidad>
    </row>
    <row>
        <key>45</key>
        <code>401054</code>
        <fullname>PIE                                                                   </fullname>
        <shortname>PIE</shortname>
        <modalidad>Rayos</modalidad>
    </row>
    <row>
        <key>48</key>
        <code>401060</code>
        <fullname>PIERNA                                                                </fullname>
        <shortname>PIER</shortname>
        <modalidad>Rayos</modalidad>
    </row>
    <row>
        <key>49</key>
        <code>401062</code>
        <fullname>PROYECCION ESPECIAL                                                   </fullname>
        <shortname>PE</shortname>
        <modalidad>Rayos</modalidad>
    </row>
    <row>
        <key>50</key>
        <code>401028</code>
        <fullname>RENAL SIMPLE                                                          </fullname>
        <shortname>RS</shortname>
        <modalidad>Rayos</modalidad>
    </row>
    <row>
        <key>51</key>
        <code>401053</code>
        <fullname>SACROCOXIS                                                            </fullname>
        <shortname>SC</shortname>
        <modalidad>Rayos</modalidad>
    </row>
    <row>
        <key>52</key>
        <code>401053</code>
        <fullname>SACROILIACAS                                                          </fullname>
        <shortname>SI</shortname>
        <modalidad>Rayos</modalidad>
    </row>
    <row>
        <key>53</key>
        <code>401040</code>
        <fullname>SILLA TURCA                                                           </fullname>
        <shortname>ST</shortname>
        <modalidad>Rayos</modalidad>
    </row>
    <row>
        <key>54</key>
        <code>401054</code>
        <fullname>TOBILLO                                                               </fullname>
        <shortname>TOB</shortname>
        <modalidad>Rayos</modalidad>
    </row>
    <row>
        <key>55</key>
        <code>401009</code>
        <fullname>TORAX SIMPLE                                                          </fullname>
        <shortname>TXS</shortname>
        <modalidad>Rayos</modalidad>
    </row>
    <row>
        <key>57</key>
        <code>401029</code>
        <fullname>VESICAL SIMPLE                                                        </fullname>
        <shortname>VS</shortname>
        <modalidad>Rayos</modalidad>
    </row>
    <row>
        <key>68</key>
        <code>401060</code>
        <fullname>RODILLA                                                               </fullname>
        <shortname>ROD</shortname>
        <modalidad>Rayos</modalidad>
    </row>
    <row>
        <key>70</key>
        <code>401070</code>
        <fullname>TORAX AP-L                                                            </fullname>
        <shortname>TXAPL</shortname>
        <modalidad>Rayos</modalidad>
    </row>
    <row>
        <key>88</key>
        <code>401047</code>
        <fullname>COLUMNA LUMBOSACRA FUNCIONALES                                        </fullname>
        <shortname>CLSF</shortname>
        <modalidad>Rayos</modalidad>
    </row>
    <row>
        <key>264</key>
        <code>401010</code>
        <fullname>MAMOGRAFIAS                                                           </fullname>
        <shortname>MAMO</shortname>
        <modalidad>Mamografias</modalidad>
    </row>
    <row>
        <key>344</key>
        <code>401024</code>
        <fullname>EED NIÑOS                                                             </fullname>
        <shortname>EED</shortname>
        <modalidad>Digestivo</modalidad>
    </row>
    <row>
        <key>346</key>
        <code>401057</code>
        <fullname>EDAD OSEA RODILLA                                                     </fullname>
        <shortname>EOR</shortname>
        <modalidad>Rayos</modalidad>
    </row>
    <row>
        <key>347</key>
        <code>401059</code>
        <fullname>MUÑECA F-L OBLICUA                                                    </fullname>
        <shortname>MTO</shortname>
        <modalidad>Rayos</modalidad>
    </row>
    <row>
        <key>348</key>
        <code>401130</code>
        <fullname>PLACA EXTRA MAMOGRAFIA C/U                                            </fullname>
        <shortname>MPE</shortname>
        <modalidad>Mamografias</modalidad>
    </row>
    <row>
        <key>349</key>
        <code>401063</code>
        <fullname>TUNEL INTERCODILEO                                                    </fullname>
        <shortname>TI</shortname>
        <modalidad>Rayos</modalidad>
    </row>
    <row>
        <key>351</key>
        <code>404019</code>
        <fullname>ECO DOPPLER COLOR                                                     </fullname>
        <shortname>EDOC</shortname>
        <modalidad>Doppler</modalidad>
    </row>
    <row>
        <key>352</key>
        <code>1701045</code>
        <fullname>ECOCARDIOGRAMA DOPPLER COLOR                                          </fullname>
        <shortname>ECD</shortname>
        <modalidad>Ecocardiograma</modalidad>
    </row>
    <row>
        <key>353</key>
        <code>404003</code>
        <fullname>ECO ABDOMINAL                                                         </fullname>
        <shortname>EA</shortname>
        <modalidad>Ecos Simples</modalidad>
    </row>
    <row>
        <key>354</key>
        <code>404009</code>
        <fullname>ECO PELVIANA MASCULI                                                  </fullname>
        <shortname>EPM</shortname>
        <modalidad>Ecos Simples</modalidad>
    </row>
    <row>
        <key>355</key>
        <code>404010</code>
        <fullname>ECO RENAL BILATERAL                                                   </fullname>
        <shortname>ER</shortname>
        <modalidad>Ecos Simples</modalidad>
    </row>
    <row>
        <key>357</key>
        <code>404014</code>
        <fullname>ECO TESTICULAR                                                        </fullname>
        <shortname>ET</shortname>
        <modalidad>Ecos Simples</modalidad>
    </row>
    <row>
        <key>359</key>
        <code>404006</code>
        <fullname>ECO GINECOLOGICA                                                      </fullname>
        <shortname>EG</shortname>
        <modalidad>Ecos Especiales</modalidad>
    </row>
    <row>
        <key>368</key>
        <code>401110</code>
        <fullname>MAMOGRAFIA UNILATERAL                                                 </fullname>
        <shortname>MAMOU</shortname>
        <modalidad>Mamografias</modalidad>
    </row>
    <row>
        <key>369</key>
        <code>401027</code>
        <fullname>PIELOGRAFIA                                                           </fullname>
        <shortname>PIELO</shortname>
        <modalidad>Pielos</modalidad>
    </row>
    <row>
        <key>370</key>
        <code>403001</code>
        <fullname>CEREBRO                                                               </fullname>
        <shortname>TC</shortname>
        <modalidad>TAC MC 1</modalidad>
    </row>
    <row>
        <key>386</key>
        <code>1801001-3 </code>
        <fullname>ENDOSCOPIA DIGESTIVA                                                  </fullname>
        <shortname>EDA</shortname>
        <modalidad>Endoscopias</modalidad>
    </row>
    <row>
        <key>390</key>
        <code>404015</code>
        <fullname>ECO TIROIDEA                                                          </fullname>
        <shortname>ETI</shortname>
        <modalidad>Ecos Simples</modalidad>
    </row>
    <row>
        <key>391</key>
        <code>404016</code>
        <fullname>ECO PARTES BLANDAS                                                    </fullname>
        <shortname>EPB</shortname>
        <modalidad>Ecos Especiales</modalidad>
    </row>
    <row>
        <key>393</key>
        <code>404012</code>
        <fullname>ECO MAMARIA                                                           </fullname>
        <shortname>EM</shortname>
        <modalidad>Ecos Simples</modalidad>
    </row>
    <row>
        <key>395</key>
        <code>401006</code>
        <fullname>CAVIDADES CARDIACAS                                                   </fullname>
        <shortname>CC</shortname>
        <modalidad>Rayos</modalidad>
    </row>
    <row>
        <key>418</key>
        <code>401060</code>
        <fullname>EXTREMIDADES INFERIORES                                               </fullname>
        <shortname>EI</shortname>
        <modalidad>Rayos</modalidad>
    </row>
    <row>
        <key>423</key>
        <code>801005</code>
        <fullname>BIOPSIA                                                               </fullname>
        <shortname>BPS</shortname>
        <modalidad>Procedimientos</modalidad>
    </row>
    <row>
        <key>426</key>
        <code>401004</code>
        <fullname>TORAX PLACA EXTRA                                                     </fullname>
        <shortname>TXPE</shortname>
        <modalidad>Rayos</modalidad>
    </row>
    <row>
        <key>428</key>
        <code>401058</code>
        <fullname>ESCAFOIDES                                                            </fullname>
        <shortname>ESC</shortname>
        <modalidad>Rayos</modalidad>
    </row>
    <row>
        <key>465</key>
        <code>401014</code>
        <fullname>ABDOMEN SIMPLE PROYECCION COMPLEMENTARIA                              </fullname>
        <shortname>ABDPC</shortname>
        <modalidad>Rayos</modalidad>
    </row>
    <row>
        <key>467</key>
        <code>404005</code>
        <fullname>ECO TRANSVAGINAL                                                      </fullname>
        <shortname>ETV</shortname>
        <modalidad>Ecos Especiales</modalidad>
    </row>
    <row>
        <key>468</key>
        <code>404006</code>
        <fullname>ECO OBSTETRICA                                                        </fullname>
        <shortname>EO</shortname>
        <modalidad>Ecos Especiales</modalidad>
    </row>
    <row>
        <key>469</key>
        <code>401151</code>
        <fullname>PELVIS LACTANTE O MENOR SEIS AÑOS                                     </fullname>
        <shortname>PELÑ</shortname>
        <modalidad>Rayos</modalidad>
    </row>
    <row>
        <key>470</key>
        <code>401151</code>
        <fullname>CADERA O COXOFEMORAL LACTANTE O MENOR SEIS AÑOS                       </fullname>
        <shortname>CADÑ</shortname>
        <modalidad>Rayos</modalidad>
    </row>
    <row>
        <key>471</key>
        <code>404019</code>
        <fullname>DOPPLER GINECOLOGICO                                                  </fullname>
        <shortname>EDGINE</shortname>
        <modalidad>Ecos Especiales</modalidad>
    </row>
    <row>
        <key>481</key>
        <code>404006</code>
        <fullname>ECO PELVIANA FEMENINA                                                 </fullname>
        <shortname>EPF</shortname>
        <modalidad>Ecos Simples</modalidad>
    </row>
    <row>
        <key>485</key>
        <code>404005</code>
        <fullname>ECO TV OBSTETRICA                                                     </fullname>
        <shortname>ETVO</shortname>
        <modalidad>Ecos Especiales</modalidad>
    </row>
    <row>
        <key>486</key>
        <code>404119</code>
        <fullname>ECO DOPPLER CAROTIDEO                                                 </fullname>
        <shortname>EDC</shortname>
        <modalidad>Doppler</modalidad>
    </row>
    <row>
        <key>487</key>
        <code>404118</code>
        <fullname>ECO DOPPLER VASC VEN                                                  </fullname>
        <shortname>ED</shortname>
        <modalidad>Doppler</modalidad>
    </row>
    <row>
        <key>488</key>
        <code>404121</code>
        <fullname>ECO DOPPLER ABDOMINAL O VASOS TESTICULAR                              </fullname>
        <shortname>EDVT</shortname>
        <modalidad>Doppler</modalidad>
    </row>
    <row>
        <key>489</key>
        <code>404122</code>
        <fullname>ECO DOPPLER VASOS PLACENTARIOS                                        </fullname>
        <shortname>EDVP</shortname>
        <modalidad>Doppler</modalidad>
    </row>
    <row>
        <key>490</key>
        <code>405001</code>
        <fullname>CEREBRO                                                               </fullname>
        <shortname>RMCER</shortname>
        <modalidad>Resonancia Magnetica</modalidad>
    </row>
    <row>
        <key>491</key>
        <code>405002</code>
        <fullname>SILLA TURCA                                                           </fullname>
        <shortname>RMST</shortname>
        <modalidad>Resonancia Magnetica</modalidad>
    </row>
    <row>
        <key>492</key>
        <code>405003</code>
        <fullname>ORBITAS                                                               </fullname>
        <shortname>RMO</shortname>
        <modalidad>Resonancia Magnetica</modalidad>
    </row>
    <row>
        <key>493</key>
        <code>405003</code>
        <fullname>MAXILOFACIAL                                                          </fullname>
        <shortname>RNMX</shortname>
        <modalidad>Resonancia Magnetica</modalidad>
    </row>
    <row>
        <key>494</key>
        <code>405004</code>
        <fullname>ART. TEMPOROMANDIBULAR                                                </fullname>
        <shortname>RMAT</shortname>
        <modalidad>Resonancia Magnetica</modalidad>
    </row>
    <row>
        <key>495</key>
        <code>405005</code>
        <fullname>COLUMNA CERVICAL                                                      </fullname>
        <shortname>RMCC</shortname>
        <modalidad>Resonancia Magnetica</modalidad>
    </row>
    <row>
        <key>496</key>
        <code>405006</code>
        <fullname>COLUMNA DORSAL                                                        </fullname>
        <shortname>RMCD</shortname>
        <modalidad>Resonancia Magnetica</modalidad>
    </row>
    <row>
        <key>497</key>
        <code>405007</code>
        <fullname>COLUMNA LUMBAR                                                        </fullname>
        <shortname>RMCL</shortname>
        <modalidad>Resonancia Magnetica</modalidad>
    </row>
    <row>
        <key>498</key>
        <code>405008</code>
        <fullname>ANGIO CEREBRAL ARTERIAL Y VENOSA                                      </fullname>
        <shortname>ANGIORM</shortname>
        <modalidad>Resonancia Magnetica</modalidad>
    </row>
    <row>
        <key>499</key>
        <code>405010</code>
        <fullname>ABDOMEN TOTAL                                                         </fullname>
        <shortname>RNA</shortname>
        <modalidad>Resonancia Magnetica</modalidad>
    </row>
    <row>
        <key>500</key>
        <code>405011</code>
        <fullname>PELVIS SOLO OSEA                                                      </fullname>
        <shortname>RMPEL</shortname>
        <modalidad>Resonancia Magnetica</modalidad>
    </row>
    <row>
        <key>501</key>
        <code>405012</code>
        <fullname>ABDOMEN Y PELVIS                                                      </fullname>
        <shortname>RNAP</shortname>
        <modalidad>Resonancia Magnetica</modalidad>
    </row>
    <row>
        <key>502</key>
        <code>405098</code>
        <fullname>COLANGIORESONANCIA                                                    </fullname>
        <shortname>COLANG</shortname>
        <modalidad>Resonancia Magnetica</modalidad>
    </row>
    <row>
        <key>514</key>
        <code>405200</code>
        <fullname>FOSA POSTERIOR Y/U OIDOS                                              </fullname>
        <shortname>FPOST</shortname>
        <modalidad>Resonancia Magnetica</modalidad>
    </row>
    <row>
        <key>515</key>
        <code>401055</code>
        <fullname>CLAVICULA                                                             </fullname>
        <shortname>CLA</shortname>
        <modalidad>Rayos</modalidad>
    </row>
    <row>
        <key>517</key>
        <code>405200</code>
        <fullname>ANGULO PONTOCEREBELOSO                                                </fullname>
        <shortname>RM APC</shortname>
        <modalidad>Resonancia Magnetica</modalidad>
    </row>
    <row>
        <key>519</key>
        <code>405200</code>
        <fullname>RM SACROILIACA                                                        </fullname>
        <shortname>RM SACRO</shortname>
        <modalidad>Resonancia Magnetica</modalidad>
    </row>
    <row>
        <key>550</key>
        <code>405016</code>
        <fullname>RNM COL TOTA (C,D,L)                                                  </fullname>
        <shortname>RM COL TOT</shortname>
        <modalidad>Resonancia Magnetica</modalidad>
    </row>
    <row>
        <key>554</key>
        <code>405013</code>
        <fullname>RODILLA UNILATERAL                                                    </fullname>
        <shortname>RMROD</shortname>
        <modalidad>Resonancia Magnetica</modalidad>
    </row>
    <row>
        <key>556</key>
        <code>405014</code>
        <fullname>CUELLO                                                                </fullname>
        <shortname>RMCU</shortname>
        <modalidad>Resonancia Magnetica</modalidad>
    </row>
    <row>
        <key>558</key>
        <code>405030</code>
        <fullname>MUSLO                                                                 </fullname>
        <shortname>RMMUSLO</shortname>
        <modalidad>Resonancia Magnetica</modalidad>
    </row>
    <row>
        <key>561</key>
        <code>401059</code>
        <fullname>TOBILLO F-L OBLICUA                                                   </fullname>
        <shortname>TFLO</shortname>
        <modalidad>Rayos</modalidad>
    </row>
    <row>
        <key>562</key>
        <code>405014</code>
        <fullname>HOMBRO                                                                </fullname>
        <shortname>RMH</shortname>
        <modalidad>Resonancia Magnetica</modalidad>
    </row>
    <row>
        <key>563</key>
        <code>405026</code>
        <fullname>CODO                                                                  </fullname>
        <shortname>RNCO</shortname>
        <modalidad>Resonancia Magnetica</modalidad>
    </row>
    <row>
        <key>564</key>
        <code>405029</code>
        <fullname>PIERNA                                                                </fullname>
        <shortname>RMPIERNA</shortname>
        <modalidad>Resonancia Magnetica</modalidad>
    </row>
    <row>
        <key>565</key>
        <code>405015</code>
        <fullname>PIE                                                                   </fullname>
        <shortname>RMPIE</shortname>
        <modalidad>Resonancia Magnetica</modalidad>
    </row>
    <row>
        <key>566</key>
        <code>405014</code>
        <fullname>BRAZO                                                                 </fullname>
        <shortname>RNB</shortname>
        <modalidad>Resonancia Magnetica</modalidad>
    </row>
    <row>
        <key>567</key>
        <code>405014</code>
        <fullname>ESCAPULA                                                              </fullname>
        <shortname>RNE</shortname>
        <modalidad>Resonancia Magnetica</modalidad>
    </row>
    <row>
        <key>568</key>
        <code>405014</code>
        <fullname>ANTEBRAZO                                                             </fullname>
        <shortname>RNA</shortname>
        <modalidad>Resonancia Magnetica</modalidad>
    </row>
    <row>
        <key>569</key>
        <code>405024</code>
        <fullname>MUÑECA                                                                </fullname>
        <shortname>RNMU</shortname>
        <modalidad>Resonancia Magnetica</modalidad>
    </row>
    <row>
        <key>570</key>
        <code>405014</code>
        <fullname>MANO                                                                  </fullname>
        <shortname>RNMA</shortname>
        <modalidad>Resonancia Magnetica</modalidad>
    </row>
    <row>
        <key>571</key>
        <code>405015</code>
        <fullname>TOBILLO                                                               </fullname>
        <shortname>RMTOB</shortname>
        <modalidad>Resonancia Magnetica</modalidad>
    </row>
    <row>
        <key>572</key>
        <code>4050200</code>
        <fullname>CADERA                                                                </fullname>
        <shortname>RMCAD</shortname>
        <modalidad>Resonancia Magnetica</modalidad>
    </row>
    <row>
        <key>573</key>
        <code>401010</code>
        <fullname>MAMOGRAFIA BILATERAL                                                  </fullname>
        <shortname>MAMO</shortname>
        <modalidad>Mamografias</modalidad>
    </row>
    <row>
        <key>574</key>
        <code>401110</code>
        <fullname>MAMOGRAFIA UNILAT                                                     </fullname>
        <shortname>MU</shortname>
        <modalidad>Mamografias</modalidad>
    </row>
    <row>
        <key>576</key>
        <code>401130</code>
        <fullname>PROYEC. MAMA                                                          </fullname>
        <shortname>PM</shortname>
        <modalidad>Rayos</modalidad>
    </row>
    <row>
        <key>578</key>
        <code>403002</code>
        <fullname>SILLA TURCA                                                           </fullname>
        <shortname>TST</shortname>
        <modalidad>TAC MC 1</modalidad>
    </row>
    <row>
        <key>579</key>
        <code>403003</code>
        <fullname>ANGULO PONTOCEREBELO                                                  </fullname>
        <shortname>TAP</shortname>
        <modalidad>TAC MC 1</modalidad>
    </row>
    <row>
        <key>580</key>
        <code>403004</code>
        <fullname>CORTES CORONALES (eliminado por FNS 01-2017)                          </fullname>
        <shortname>TCC</shortname>
        <modalidad>TAC MC 1</modalidad>
    </row>
    <row>
        <key>581</key>
        <code>403006</code>
        <fullname>TEMPORAL OIDO                                                         </fullname>
        <shortname>TTO</shortname>
        <modalidad>TAC MC 1</modalidad>
    </row>
    <row>
        <key>582</key>
        <code>403007</code>
        <fullname>ORBITAS MAXILOFACIAL                                                  </fullname>
        <shortname>TOM</shortname>
        <modalidad>TAC MC 1</modalidad>
    </row>
    <row>
        <key>583</key>
        <code>403008</code>
        <fullname>COLUMNA CERVICAL                                                      </fullname>
        <shortname>TCC</shortname>
        <modalidad>TAC MC 1</modalidad>
    </row>
    <row>
        <key>584</key>
        <code>403009</code>
        <fullname>COLUMNA DORSAL O LUM                                                  </fullname>
        <shortname>TCD</shortname>
        <modalidad>TAC MC 1</modalidad>
    </row>
    <row>
        <key>585</key>
        <code>403010</code>
        <fullname>ESP. ADICIONAL (eliminado por FNS 01-2017)                            </fullname>
        <shortname>EA</shortname>
        <modalidad>TAC MC 1</modalidad>
    </row>
    <row>
        <key>586</key>
        <code>403012</code>
        <fullname>CUELLO, PARTES BLAN                                                   </fullname>
        <shortname>TCPB</shortname>
        <modalidad>TAC MC 1</modalidad>
    </row>
    <row>
        <key>587</key>
        <code>403013</code>
        <fullname>TORAX TOTAL                                                           </fullname>
        <shortname>TT</shortname>
        <modalidad>TAC MC 1</modalidad>
    </row>
    <row>
        <key>588</key>
        <code>403014</code>
        <fullname>ABDOMEN                                                               </fullname>
        <shortname>TA</shortname>
        <modalidad>TAC MC 1</modalidad>
    </row>
    <row>
        <key>589</key>
        <code>403016</code>
        <fullname>PELVIS                                                                </fullname>
        <shortname>TP</shortname>
        <modalidad>TAC MC 1</modalidad>
    </row>
    <row>
        <key>590</key>
        <code>403017</code>
        <fullname>EXTREMIDADES EST LOC                                                  </fullname>
        <shortname>TE</shortname>
        <modalidad>TAC MC 1</modalidad>
    </row>
    <row>
        <key>592</key>
        <code>403101</code>
        <fullname>ANGIOTAC CEREBRO                                                      </fullname>
        <shortname>AG</shortname>
        <modalidad>TAC MC 1</modalidad>
    </row>
    <row>
        <key>593</key>
        <code>403103</code>
        <fullname>ANGIOTAC ABDOMEN                                                      </fullname>
        <shortname>AA</shortname>
        <modalidad>TAC MC 1</modalidad>
    </row>
    <row>
        <key>594</key>
        <code>403014</code>
        <fullname>PIELOTAC                                                              </fullname>
        <shortname>PT</shortname>
        <modalidad>TAC MC 1</modalidad>
    </row>
    <row>
        <key>629</key>
        <code>501134</code>
        <fullname>DENSITOMETRIA OSEA (verif. datos)                                     </fullname>
        <shortname>DO</shortname>
        <modalidad>Densitometria</modalidad>
    </row>
    <row>
        <key>749</key>
        <code>403007</code>
        <fullname>CAVIDADES PERINASALE                                                  </fullname>
        <shortname>TCP</shortname>
        <modalidad>TAC MC 1</modalidad>
    </row>
    <row>
        <key>752</key>
        <code>403104</code>
        <fullname>ANGIO TAC CUELLO                                                      </fullname>
        <shortname>ATC</shortname>
        <modalidad>TAC MC 1</modalidad>
    </row>
    <row>
        <key>761</key>
        <code>403018</code>
        <fullname>COLUMNA DORSAL                                                        </fullname>
        <shortname>TCD</shortname>
        <modalidad>TAC MC 1</modalidad>
    </row>
    <row>
        <key>762</key>
        <code>403019</code>
        <fullname>COLUMNA LUMBAR                                                        </fullname>
        <shortname>TCL</shortname>
        <modalidad>TAC MC 1</modalidad>
    </row>
    <row>
        <key>763</key>
        <code>403020</code>
        <fullname>ABDOMEN PELVIS                                                        </fullname>
        <shortname>TABDPEL</shortname>
        <modalidad>TAC MC 1</modalidad>
    </row>
    <row>
        <key>765</key>
        <code>403105</code>
        <fullname>ANGIOTAC PELVIS                                                       </fullname>
        <shortname>ATP</shortname>
        <modalidad>TAC MC 1</modalidad>
    </row>
    <row>
        <key>946</key>
        <code>405018</code>
        <fullname>ANGIORESONANCIA DE CUELLO                                             </fullname>
        <shortname>ANCUELLO</shortname>
        <modalidad>Resonancia Magnetica</modalidad>
    </row>
    <row>
        <key>947</key>
        <code>405020</code>
        <fullname>ANGIORESONANCIA ABDOMEN                                               </fullname>
        <shortname>ANGIOABD</shortname>
        <modalidad>Resonancia Magnetica</modalidad>
    </row>
    <row>
        <key>950</key>
        <code>405021</code>
        <fullname>ANGIORESONANCIA PELVIS                                                </fullname>
        <shortname>AMGIOPEL</shortname>
        <modalidad>Resonancia Magnetica</modalidad>
    </row>
    <row>
        <key>951</key>
        <code>405022</code>
        <fullname>ANGIORESONANCIA EXTREMIDAD  SUPERIOR  UNILATERAL                      </fullname>
        <shortname>ANESUNI</shortname>
        <modalidad>Resonancia Magnetica</modalidad>
    </row>
    <row>
        <key>952</key>
        <code>405023</code>
        <fullname>ANGIORESONANCIA EXTREMIDAD INFERIOR BILATERAL                         </fullname>
        <shortname>ANEEIIBIL</shortname>
        <modalidad>Resonancia Magnetica</modalidad>
    </row>
    <row>
        <key>953</key>
        <code>405009</code>
        <fullname>RESONANCIA MAGNETICA TORAX                                            </fullname>
        <shortname>RMTX</shortname>
        <modalidad>Resonancia Magnetica</modalidad>
    </row>
    <row>
        <key>954</key>
        <code>405031</code>
        <fullname>RESONANCIA MAGNETICA DE MAMA (BILATERAL)                              </fullname>
        <shortname>RMMAMA</shortname>
        <modalidad>Resonancia Magnetica</modalidad>
    </row>
</root>
